echo_downloader/__init__.py
echo_downloader/config.py
echo_downloader/config.yaml
echo_downloader/domain.py
echo_downloader/downloader.py
echo_downloader/helpers.py
echo_downloader/main.py
echo_downloader/merger.py
echo_downloader/ui.py
echo_downloader-1.0.3.dist-info/licenses/LICENSE
echo_downloader-1.0.3.dist-info/METADATA
echo_downloader-1.0.3.dist-info/WHEEL
echo_downloader-1.0.3.dist-info/entry_points.txt
echo_downloader-1.0.3.dist-info/top_level.txt
echo_downloader-1.0.3.dist-info/RECORD
